tola_payments/__init__.py
tola_payments/testing.py
tola_payments-1.0.1.dist-info/LICENSE
tola_payments-1.0.1.dist-info/METADATA
tola_payments-1.0.1.dist-info/WHEEL
tola_payments-1.0.1.dist-info/top_level.txt
tola_payments-1.0.1.dist-info/RECORD
