Metadata-Version: 2.1
Name: tola-payments
Version: 1.0.1
Summary: A python package to easy push payment integration with Tola Payments with Mpesa, TigoPesa, and AirtelMoney Tanzania
License-File: LICENSE
Requires-Dist: phonenumbers
Requires-Dist: tanzania-mno
Requires-Dist: python-decouple
